{"ExifVersion": "0230", "ShutterSpeedValue": [6965784, 1000000], "ApertureValue": [6918863, 1000000], "DateTimeOriginal": "2018:06:23 12:02:05", "DateTimeDigitized": "2018:06:23 12:02:05", "ExposureBiasValue": [0, 6], "MaxApertureValue": [36, 10], "MeteringMode": 5, "LightSource": 0, "Flash": 16, "FocalLength": [180, 10], "ColorSpace": 1, "WhiteBalance": 0, "FocalLengthIn35mmFilm": 27, "FocalPlaneXResolution": [84928060, 32768], "FocalPlaneYResolution": [84928060, 32768], "FocalPlaneResolutionUnit": 3, "SubsecTimeOriginal": "75", "SubsecTimeDigitized": "75", "Sharpness": 0, "SubjectDistanceRange": 0, "Model": "NIKON D3400", "Make": "NIKON CORPORATION", "SensingMethod": 2, "Copyright": "MIKE", "FileSource": "\u0003", "ExposureTime": [1, 125], "XResolution": [240, 1], "YResolution": [240, 1], "FNumber": [11, 1], "SceneType": "\u0001", "ExposureProgram": 0, "CFAPattern": "\u0002\u0000\u0002\u0000\u0000\u0001\u0001\u0002", "CustomRendered": 0, "ISOSpeedRatings": 100, "ResolutionUnit": 2, "ExposureMode": 0, "34864": 2, "BodySerialNumber": "6204314", "34866": 100, "LensSpecification": [[180, 10], [550, 10], [35, 10], [56, 10]], "LensModel": "18.0-55.0 mm f/3.5-5.6", "Software": "Adobe Photoshop Lightroom 6.7 (Windows)", "DateTime": "2018:07:27 00:55:09", "SceneCaptureType": 1, "GainControl": 0, "Contrast": 0, "Saturation": 0, "ExifOffset": 234}